Metadata-Version: 2.1
Name: omccolors
Version: 0.1.0
Summary: Generation of Order of Magnitude Colors from Matplotlib Color Scales
Home-page: https://arxiv.org/abs/2207.12399
Author: Daniel Braun
Author-email: braun@cs.uni-koeln.de
License: MIT
Platform: UNKNOWN
Classifier: Programming Language :: Python :: 3
Classifier: Operating System :: OS Independent
Requires-Python: >=3.10
License-File: LICENSE.txt
